diffcalculus/__differentiate__.py
diffcalculus/__init__.py
diffcalculus/errors.py
diffcalculus/functions.py
diffcalculus-0.1.6.dist-info/LICENSE
diffcalculus-0.1.6.dist-info/METADATA
diffcalculus-0.1.6.dist-info/WHEEL
diffcalculus-0.1.6.dist-info/top_level.txt
diffcalculus-0.1.6.dist-info/RECORD
